opentelemetry/resource/detector/containerid/__init__.py
opentelemetry/resource/detector/containerid/version.py
opentelemetry_resource_detector_containerid-0.60b1.dist-info/METADATA
opentelemetry_resource_detector_containerid-0.60b1.dist-info/WHEEL
opentelemetry_resource_detector_containerid-0.60b1.dist-info/entry_points.txt
opentelemetry_resource_detector_containerid-0.60b1.dist-info/licenses/LICENSE
opentelemetry_resource_detector_containerid-0.60b1.dist-info/RECORD
